renku_sphinx_theme/__init__.py
renku_sphinx_theme/about.html
renku_sphinx_theme/compile_scss_config.json
renku_sphinx_theme/theme.conf
renku_sphinx_theme/version.py
renku_sphinx_theme/static/custom.css
renku_sphinx_theme/static/custom.scss
renku_sphinx_theme/static/favicon.png
renku_sphinx_theme/static/fonts.css
renku_sphinx_theme/static/fonts/calcutta/Calcutta-Bold.eot
renku_sphinx_theme/static/fonts/calcutta/Calcutta-Bold.otf
renku_sphinx_theme/static/fonts/calcutta/Calcutta-Bold.svg
renku_sphinx_theme/static/fonts/calcutta/Calcutta-Bold.ttf
renku_sphinx_theme/static/fonts/calcutta/Calcutta-Bold.woff
renku_sphinx_theme/static/fonts/calcutta/Calcutta-Medium.eot
renku_sphinx_theme/static/fonts/calcutta/Calcutta-Medium.otf
renku_sphinx_theme/static/fonts/calcutta/Calcutta-Medium.svg
renku_sphinx_theme/static/fonts/calcutta/Calcutta-Medium.ttf
renku_sphinx_theme/static/fonts/calcutta/Calcutta-Medium.woff
renku_sphinx_theme/static/fonts/calcutta/Calcutta-Regular.eot
renku_sphinx_theme/static/fonts/calcutta/Calcutta-Regular.otf
renku_sphinx_theme/static/fonts/calcutta/Calcutta-Regular.svg
renku_sphinx_theme/static/fonts/calcutta/Calcutta-Regular.ttf
renku_sphinx_theme/static/fonts/calcutta/Calcutta-Regular.woff
renku_sphinx_theme-0.5.2.dist-info/licenses/AUTHORS.rst
renku_sphinx_theme-0.5.2.dist-info/licenses/LICENSE
renku_sphinx_theme-0.5.2.dist-info/METADATA
renku_sphinx_theme-0.5.2.dist-info/WHEEL
renku_sphinx_theme-0.5.2.dist-info/entry_points.txt
renku_sphinx_theme-0.5.2.dist-info/top_level.txt
renku_sphinx_theme-0.5.2.dist-info/RECORD
