Metadata-Version: 2.4
Name: renku-sphinx-theme
Version: 0.5.2
Summary: A Sphinx theme for Renku documentation.
Home-page: https://github.com/SwissDataScienceCenter/renku-sphinx-theme
Author: Swiss Data Science Center (SDSC)
Author-email: contact@datascience.ch
License: Apache License 2.0
Keywords: Renku Sphinx theme
Platform: any
Classifier: Intended Audience :: Developers
Classifier: License :: OSI Approved :: Apache Software License
Classifier: Operating System :: OS Independent
Classifier: Topic :: Documentation
Classifier: Topic :: Software Development :: Documentation
Classifier: Programming Language :: Python :: 3
Classifier: Programming Language :: Python :: 3.6
Classifier: Programming Language :: Python :: 3.7
Classifier: Programming Language :: Python :: 3.8
License-File: LICENSE
License-File: AUTHORS.rst
Requires-Dist: Sphinx<10.0.0,>=1.6.3
Requires-Dist: sphinx-rtd-theme<3.2,>=0.5.0
Provides-Extra: docs
Requires-Dist: Sphinx<10.0.0,>=1.6.3; extra == "docs"
Requires-Dist: sphinx-rtd-theme<3.2,>=0.5.0; extra == "docs"
Provides-Extra: dev
Requires-Dist: libsass~=0.23.0; extra == "dev"
Provides-Extra: tests
Requires-Dist: check-manifest>=0.25; extra == "tests"
Requires-Dist: isort>=4.2.2; extra == "tests"
Requires-Dist: pydocstyle>=1.0.0; extra == "tests"
Requires-Dist: twine<7.0,>=4.0; extra == "tests"
Requires-Dist: pkginfo<1.13; extra == "tests"
Requires-Dist: setuptools; extra == "tests"
Requires-Dist: wheel; extra == "tests"
Provides-Extra: all
Requires-Dist: Sphinx<10.0.0,>=1.6.3; extra == "all"
Requires-Dist: sphinx-rtd-theme<3.2,>=0.5.0; extra == "all"
Requires-Dist: libsass~=0.23.0; extra == "all"
Requires-Dist: check-manifest>=0.25; extra == "all"
Requires-Dist: isort>=4.2.2; extra == "all"
Requires-Dist: pydocstyle>=1.0.0; extra == "all"
Requires-Dist: twine<7.0,>=4.0; extra == "all"
Requires-Dist: pkginfo<1.13; extra == "all"
Requires-Dist: setuptools; extra == "all"
Requires-Dist: wheel; extra == "all"
Dynamic: author
Dynamic: author-email
Dynamic: classifier
Dynamic: description
Dynamic: description-content-type
Dynamic: home-page
Dynamic: keywords
Dynamic: license
Dynamic: license-file
Dynamic: platform
Dynamic: provides-extra
Dynamic: requires-dist
Dynamic: summary
